{"url": "http://www.language-archives.org/language/agv", "code": "agv", "coords": ["14.6254", "121.453"], "name": "Remontado Dumagat", "resources": {"Other resources about the language": {"count": 1, "resources": [{"url": "http://www.language-archives.org/item/oai:ethnologue.com:agv", "text": "<i>Dumagat, Remontado: a language of Philippines.</i> n.a. 2013. SIL International.\n ", "name": "oai:ethnologue.com:agv", "is_online": true}]}, "Language descriptions": {"count": 1, "resources": [{"url": "http://www.language-archives.org/item/oai:glottolog.org:remo1247", "text": "<i>Glottolog 2.6 Resources for Remontado Agta.</i> n.a. 2014. Max Planck Institute for the Science of Human History.\n ", "name": "oai:glottolog.org:remo1247", "is_online": true}]}}}