{"url": "http://www.language-archives.org/language/apl", "code": "apl", "coords": ["33.36", "33.191", "-105.929", "-105.71"], "name": "Lipan Apache language", "resources": {"Other resources about the language": {"count": 2, "resources": [{"url": "http://www.language-archives.org/item/oai:ethnologue.com:apl", "text": "<i>Apache, Lipan: a language of United States.</i> n.a. 2013. SIL International.\n ", "name": "oai:ethnologue.com:apl", "is_online": true}, {"url": "http://www.language-archives.org/item/oai:linguistlist.org:lang_apl", "text": "<i>LINGUIST List Resources for Apache, Lipan.</i> Damir Cavar, Director of Linguist List (editor); Malgorzata E. Cavar, Director of Linguist List (editor). 2015-12-23. The LINGUIST List (www.linguistlist.org).\n ", "name": "oai:linguistlist.org:lang_apl", "is_online": true}]}, "Language descriptions": {"count": 1, "resources": [{"url": "http://www.language-archives.org/item/oai:glottolog.org:lipa1241", "text": "<i>Glottolog 2.6 Resources for Lipan Apache.</i> n.a. 2015. Max Planck Institute for the Science of Human History.\n ", "name": "oai:glottolog.org:lipa1241", "is_online": true}]}}}