{"url": "http://www.language-archives.org/language/bkj", "code": "bkj", "coords": ["4.116", "3.153", "16.021", "16.434"], "name": "Pande language", "resources": {"Other resources about the language": {"count": 1, "resources": [{"url": "http://www.language-archives.org/item/oai:ethnologue.com:bkj", "text": "<i>Pande: a language of Central African Republic.</i> n.a. 2013. SIL International.\n ", "name": "oai:ethnologue.com:bkj", "is_online": true}]}, "Language descriptions": {"count": 1, "resources": [{"url": "http://www.language-archives.org/item/oai:glottolog.org:pand1264", "text": "<i>Glottolog 2.6 Resources for Pande.</i> n.a. 2015. Max Planck Institute for the Science of Human History.\n ", "name": "oai:glottolog.org:pand1264", "is_online": true}]}}}