{"url": "http://www.language-archives.org/language/bog", "code": "bog", "coords": ["12.651", "12.651", "-8.00136", "-8.00136"], "name": "Bamako Sign Language", "resources": {"Other resources in the language": {"count": 1, "resources": [{"url": "http://www.language-archives.org/item/oai:elar.soas.ac.uk:0108", "text": "<i>Un Corpus de Reference de la Langues des Signes Malienne.</i> Victoria Nyst (depositor); Endangered Languages Documentation Programme (sponsor). start=2007-09-01; end=2010-09-01;. Endangered Languages Archive.\n ", "name": "oai:elar.soas.ac.uk:0108", "is_online": true}]}, "Other resources about the language": {"count": 1, "resources": [{"url": "http://www.language-archives.org/item/oai:ethnologue.com:bog", "text": "<i>Bamako Sign Language: a language of Mali.</i> n.a. 2013. SIL International.\n ", "name": "oai:ethnologue.com:bog", "is_online": true}]}, "Language descriptions": {"count": 1, "resources": [{"url": "http://www.language-archives.org/item/oai:glottolog.org:bama1249", "text": "<i>Glottolog 2.6 Resources for Bamako Sign Language.</i> n.a. 2015. Max Planck Institute for the Science of Human History.\n ", "name": "oai:glottolog.org:bama1249", "is_online": true}]}}}