{"url": "http://www.language-archives.org/language/bqr", "code": "bqr", "coords": ["3.56", "2.893", "116.713", "117.311"], "name": "Burusu language", "resources": {"Other resources about the language": {"count": 1, "resources": [{"url": "http://www.language-archives.org/item/oai:ethnologue.com:bqr", "text": "<i>Burusu: a language of Indonesia.</i> n.a. 2013. SIL International.\n ", "name": "oai:ethnologue.com:bqr", "is_online": true}]}, "Language descriptions": {"count": 1, "resources": [{"url": "http://www.language-archives.org/item/oai:glottolog.org:buru1304", "text": "<i>Glottolog 2.6 Resources for Burusu.</i> n.a. 2015. Max Planck Institute for the Science of Human History.\n ", "name": "oai:glottolog.org:buru1304", "is_online": true}]}}}