{"url": "http://www.language-archives.org/language/cnk", "code": "cnk", "coords": ["22.8713", "92.9895"], "name": "Khumi Chin", "resources": {"Lexical resources": {"count": 1, "resources": [{"url": "http://www.language-archives.org/item/oai:crubadan.org:cnk", "text": "<i>Cr&#250;bad&#225;n language data for Khumi Chin.</i> Kevin Scannell. 2015. The Cr&#250;bad&#225;n Project.\n ", "name": "oai:crubadan.org:cnk", "is_online": true}]}, "Other resources about the language": {"count": 2, "resources": [{"url": "http://www.language-archives.org/item/oai:sil.org:41669", "text": "<i>The Kuki-Chin Communities of Bangladesh: A Sociolinguistic Survey.</i> Kim, Amy; Roy, Palash; Sangma, Mridul. 2008. SIL Electronic Survey Reports 2011-025.\n ", "name": "oai:sil.org:41669", "is_online": true}, {"url": "http://www.language-archives.org/item/oai:ethnologue.com:cnk", "text": "<i>Chin, Khumi: a language of Myanmar.</i> n.a. 2013. SIL International.\n ", "name": "oai:ethnologue.com:cnk", "is_online": true}]}, "Language descriptions": {"count": 2, "resources": [{"url": "http://www.language-archives.org/item/oai:glottolog.org:khum1248", "text": "<i>Glottolog 2.7 Resources for Khumi Chin.</i> n.a. 2015. Max Planck Institute for the Science of Human History.\n ", "name": "oai:glottolog.org:khum1248", "is_online": true}, {"url": "http://www.language-archives.org/item/oai:wals.info:khu", "text": "<i>WALS Online Resources for Khumi.</i> n.a. 2008. Max Planck Institute for Evolutionary Anthropology.\n ", "name": "oai:wals.info:khu", "is_online": true}]}}}