{"url": "http://www.language-archives.org/language/dux", "code": "dux", "coords": ["11.208", "10.785", "-6.188", "-5.53"], "name": "Duungooma language", "resources": {"Other resources about the language": {"count": 2, "resources": ["<li><span class=\"online_indicator\">ONLINE</span><i>Enquete linguistique sur la langue Duungoma: une langue samogo parl&#233;e au Mali et au Burkina Faso.</i> Hochstetler, J. Lee. 1999. SIL Electronic Survey Reports 1999-002.\n <a href=\"/item/oai:sil.org:9200\">oai:sil.org:9200</a></li>", "<li><span class=\"online_indicator\">ONLINE</span><i>Duungooma: a language of Mali.</i> n.a. 2013. SIL International.\n <a href=\"/item/oai:ethnologue.com:dux\">oai:ethnologue.com:dux</a></li>"]}, "Language descriptions": {"count": 1, "resources": ["<li><span class=\"online_indicator\">ONLINE</span><i>Glottolog 2.6 Resources for Duungooma.</i> n.a. 2015. Max Planck Institute for the Science of Human History.\n <a href=\"/item/oai:glottolog.org:duun1242\">oai:glottolog.org:duun1242</a></li>"]}}}