{"url": "http://www.language-archives.org/language/dza", "code": "dza", "coords": ["10.207", "9.342", "9.156", "10.788"], "name": "Tunzu language", "resources": {"Other resources about the language": {"count": 1, "resources": ["<li><span class=\"online_indicator\">ONLINE</span><i>Tunzuii: a language of Nigeria.</i> n.a. 2013. SIL International.\n <a href=\"/item/oai:ethnologue.com:dza\">oai:ethnologue.com:dza</a></li>"]}, "Language descriptions": {"count": 1, "resources": ["<li><span class=\"online_indicator\">ONLINE</span><i>Glottolog 2.6 Resources for Tunzu.</i> n.a. 2015. Max Planck Institute for the Science of Human History.\n <a href=\"/item/oai:glottolog.org:tunz1235\">oai:glottolog.org:tunz1235</a></li>"]}}}