{"url": "http://www.language-archives.org/language/geq", "code": "geq", "coords": ["8.526", "8.405", "20.584", "20.739"], "name": "Geme language", "resources": {"Other resources about the language": {"count": 1, "resources": [{"url": "http://www.language-archives.org/item/oai:ethnologue.com:geq", "text": "<i>Geme: a language of Central African Republic.</i> n.a. 2013. SIL International.\n ", "name": "oai:ethnologue.com:geq", "is_online": true}]}, "Language descriptions": {"count": 1, "resources": [{"url": "http://www.language-archives.org/item/oai:glottolog.org:geme1244", "text": "<i>Glottolog 2.6 Resources for Geme.</i> n.a. 2014. Max Planck Institute for the Science of Human History.\n ", "name": "oai:glottolog.org:geme1244", "is_online": true}]}}}