{"url": "http://www.language-archives.org/language/gom", "code": "gom", "coords": ["15.2732", "74.2098"], "name": "Goan Konkani", "resources": {"Lexical resources": {"count": 2, "resources": [{"url": "http://www.language-archives.org/item/oai:crubadan.org:gom", "text": "<i>Cr&#250;bad&#225;n language data for Goan Konkani.</i> Kevin Scannell. 2015. The Cr&#250;bad&#225;n Project.\n ", "name": "oai:crubadan.org:gom", "is_online": true}, {"url": "http://www.language-archives.org/item/oai:crubadan.org:gom-Deva", "text": "<i>Cr&#250;bad&#225;n language data for Goan Konkani.</i> Kevin Scannell. 2015. The Cr&#250;bad&#225;n Project.\n ", "name": "oai:crubadan.org:gom-Deva", "is_online": true}]}, "Other resources about the language": {"count": 2, "resources": [{"url": "http://www.language-archives.org/item/oai:ethnologue.com:gom", "text": "<i>Konkani, Goan: a language of India.</i> n.a. 2013. SIL International.\n ", "name": "oai:ethnologue.com:gom", "is_online": true}, {"url": "http://www.language-archives.org/item/oai:linguistlist.org:lang_gom", "text": "<i>LINGUIST List Resources for Konkani, Goan.</i> Damir Cavar, Director of Linguist List (editor); Malgorzata E. Cavar, Director of Linguist List (editor). 2016-05-21. The LINGUIST List (www.linguistlist.org).\n ", "name": "oai:linguistlist.org:lang_gom", "is_online": true}]}, "Language descriptions": {"count": 1, "resources": [{"url": "http://www.language-archives.org/item/oai:glottolog.org:goan1235", "text": "<i>Glottolog 2.7 Resources for Goan Konkani.</i> n.a. 2015. Max Planck Institute for the Science of Human History.\n ", "name": "oai:glottolog.org:goan1235", "is_online": true}]}}}