{"url": "http://www.language-archives.org/language/grw", "code": "grw", "coords": ["-10.2173", "150.421"], "name": "Gweda", "resources": {"Other resources about the language": {"count": 1, "resources": [{"url": "http://www.language-archives.org/item/oai:ethnologue.com:grw", "text": "<i>Gweda: a language of Papua New Guinea.</i> n.a. 2013. SIL International.\n ", "name": "oai:ethnologue.com:grw", "is_online": true}]}, "Language descriptions": {"count": 2, "resources": [{"url": "http://www.language-archives.org/item/oai:glottolog.org:gwed1239", "text": "<i>Glottolog 2.6 Resources for Gweda.</i> n.a. 2015. Max Planck Institute for the Science of Human History.\n ", "name": "oai:glottolog.org:gwed1239", "is_online": true}, {"url": "http://www.language-archives.org/item/oai:sil.org:49078", "text": "<i>Gweda Organised Phonology Data (OPD).</i> Heineman, Paul (consultant); Knauber, Martin (consultant). 2001. SIL Language and Culture Archives.\n ", "name": "oai:sil.org:49078", "is_online": true}]}}}