{"url": "http://www.language-archives.org/language/hts", "code": "hts", "coords": ["-3.512", "-4.005", "34.795", "35.296"], "name": "Hadza language", "resources": {"Lexical resources": {"count": 1, "resources": [{"url": "http://www.language-archives.org/item/oai:rosettaproject.org:rosettaproject_hts_swadesh-1", "text": "<i>Hadza Swadesh List.</i> n.a. n.d. The Rosetta Project: A Long Now Foundation Library of Human Language.\n ", "name": "oai:rosettaproject.org:rosettaproject_hts_swadesh-1", "is_online": true}]}, "Other resources about the language": {"count": 4, "resources": [{"url": "http://www.language-archives.org/item/oai:refdb.wals.info:727", "text": "<i>The phonetic structures of Hadza.</i> Sands, Bonny; Maddieson, Ian; Ladefoged, Peter. 1996. WALS Online RefDB.\n ", "name": "oai:refdb.wals.info:727", "is_online": true}, {"url": "http://www.language-archives.org/item/oai:refdb.wals.info:851", "text": "<i>The East African click languages: a phonetic comparison.</i> Tucker, Archibald Norman; Bryan, Margaret; Woodburn, James. 1977. Zur Sprachgeschichte und Ethnohistorie in Afrika.\n ", "name": "oai:refdb.wals.info:851", "is_online": true}, {"url": "http://www.language-archives.org/item/oai:ethnologue.com:hts", "text": "<i>Hadza: a language of Tanzania.</i> n.a. 2013. SIL International.\n ", "name": "oai:ethnologue.com:hts", "is_online": true}, {"url": "http://www.language-archives.org/item/oai:linguistlist.org:lang_hts", "text": "<i>LINGUIST List Resources for Hadza.</i> Damir Cavar, Director of Linguist List (editor); Malgorzata E. Cavar, Director of Linguist List (editor). 2013-07-25. The LINGUIST List (www.linguistlist.org).\n ", "name": "oai:linguistlist.org:lang_hts", "is_online": true}]}, "Language descriptions": {"count": 3, "resources": [{"url": "http://www.language-archives.org/item/oai:glottolog.org:hadz1240", "text": "<i>Glottolog 2.6 Resources for Hadza.</i> n.a. 2014. Max Planck Institute for the Science of Human History.\n ", "name": "oai:glottolog.org:hadz1240", "is_online": true}, {"url": "http://www.language-archives.org/item/oai:phoible.org:hts", "text": "<i>PHOIBLE Online phonemic inventories for Hadza.</i> n.a. 2014. Max Planck Institute for Evolutionary Anthropology.\n ", "name": "oai:phoible.org:hts", "is_online": true}, {"url": "http://www.language-archives.org/item/oai:wals.info:had", "text": "<i>WALS Online Resources for Hadza.</i> n.a. 2008. Max Planck Institute for Evolutionary Anthropology.\n ", "name": "oai:wals.info:had", "is_online": true}]}}}