{"url": "http://www.language-archives.org/language/iku", "code": "iku", "coords": ["", "", "", ""], "name": "Inuktitut language", "resources": {"Other resources in the language": {"count": 1, "resources": [{"url": "http://www.language-archives.org/item/oai:lindat.mff.cuni.cz:11372/LRT-995", "text": "<i>LAC Inuktitut Corpus.</i> n.a. 2014. Max Planck Institute for Psycholinguistics.\n ", "name": "oai:lindat.mff.cuni.cz:11372/LRT-995", "is_online": true}]}, "Lexical resources": {"count": 2, "resources": [{"url": "http://www.language-archives.org/item/oai:crubadan.org:iu", "text": "<i>Cr&#250;bad&#225;n language data for Inuktitut.</i> Kevin Scannell. 2015. The Cr&#250;bad&#225;n Project.\n ", "name": "oai:crubadan.org:iu", "is_online": true}, {"url": "http://www.language-archives.org/item/oai:crubadan.org:iu-Latn", "text": "<i>Cr&#250;bad&#225;n language data for Inuktitut (Latin).</i> Kevin Scannell. 2015. The Cr&#250;bad&#225;n Project.\n ", "name": "oai:crubadan.org:iu-Latn", "is_online": true}]}}}