{"url": "http://www.language-archives.org/language/jmx", "code": "jmx", "coords": ["17.3003", "-98.2096"], "name": "Western Juxtlahuaca Mixtec", "resources": {"Other resources about the language": {"count": 58, "resources": [{"url": "http://www.language-archives.org/item/oai:sil.org:51002", "text": "<i>N&#225; ka&#42892;v&#237;-e ntsi&#225;&#225; hora y&#225;&#225;.</i> Rivera Rodr&#237;guez, C&#233;sar; Mendoza Salvador, Socorro; Beatham, Bruce; Brown de Beatham, Candice. 2012. Instituto Ling&#252;&#237;stico de Verano, A.C.\n ", "name": "oai:sil.org:51002", "is_online": true}, {"url": "http://www.language-archives.org/item/oai:sil.org:51003", "text": "<i>Color &#241;a&#817;&#42892;a x&#237;xi-e&#42892;.</i> Rivera Rodr&#237;guez, C&#233;sar; Mendoza Salvador, Socorro; Beatham, Bruce; Brown de Beatham, Candice. 2012. Instituto Ling&#252;&#237;stico de Verano, A.C.\n ", "name": "oai:sil.org:51003", "is_online": true}, {"url": "http://www.language-archives.org/item/oai:sil.org:43005", "text": "<i>Tu&#817;&#42892;un na&#817;   &#241;uu Ki&#817;yaa x&#237;&#42892;in na&#817; xiyo oeste &#241;uu Sku&#237;ya.</i> Beatham, Bruce (compiler); Brown de Beatham, Candice (compiler). 2011. Instituto Ling&#252;&#237;stico de Verano, A.C.\n ", "name": "oai:sil.org:43005", "is_online": true}, {"url": "http://www.language-archives.org/item/oai:sil.org:59711", "text": "<i>Leso x&#237;&#42892;in &#241;u&#817;m&#225; tu&#817;&#250;n.</i> Brown de Beatham, Candice; Flores Rodrigu&#233;z, Sergio (speaker); Flores Rodrigu&#233;z, Margarito (speaker); Beatham, Bruce. 2014. Instituto Ling&#252;&#237;stico de Verano, A.C.\n ", "name": "oai:sil.org:59711", "is_online": true}, {"url": "http://www.language-archives.org/item/oai:sil.org:59712", "text": "<i>K&#225;&#42892;vi-yo tu&#817;&#42892;un-yo.</i> Beatham, Candice. 2014. Instituto Ling&#252;&#237;stico de Verano, A.C.\n ", "name": "oai:sil.org:59712", "is_online": true}, {"url": "http://www.language-archives.org/item/oai:sil.org:12915", "text": "<i>&#191;&#193; x&#238;ni-un nd&#225;a ndo&#42892;&#243; kit&#237; k&#250;&#250;-a?.</i> Brown de Beatham, Candice (consultant). 2009. Instituto Ling&#252;&#237;stico de Verano, A.C.\n ", "name": "oai:sil.org:12915", "is_online": true}, {"url": "http://www.language-archives.org/item/oai:sil.org:43016", "text": "<i>&#209;a&#817;  koo-yo / &#209;a&#817;  &#237;yo-yo / &#209;a&#817;  ni&#817;xi&#817;yo-yo.</i> Brown de Beatham, Candice; Ram&#237;rez Flores, Esperanza (speaker). 2011. Instituto Ling&#252;&#237;stico de Verano, A.C.\n ", "name": "oai:sil.org:43016", "is_online": true}, {"url": "http://www.language-archives.org/item/oai:sil.org:59717", "text": "<i>Kit&#237; n&#225;&#42892;nu x&#237;&#42892;in kit&#237; v&#225;l&#237;.</i> Mendoza Rodrigu&#233;z, Esther; Rodrigu&#233;z Flores, Rebeca; Beatham, Candice. 2014. Instituto Ling&#252;&#237;stico de Verano, A.C.\n ", "name": "oai:sil.org:59717", "is_online": true}, {"url": "http://www.language-archives.org/item/oai:sil.org:13219", "text": "<i>&#191;Nd&#225;a &#237;ya ch&#237;tun?.</i> Brown de Beatham, Candice (consultant); Beatham, Bruce (consultant). 2009. Instituto Ling&#252;&#237;stico de Verano.\n ", "name": "oai:sil.org:13219"}, {"url": "http://www.language-archives.org/item/oai:sil.org:43023", "text": "<i>Xi&#817;t&#225; k&#225;&#42892;nu.</i> Brown de Beatham, Candice; Santos P&#233;rez, Fabiola (speaker). 2011. Instituto Ling&#252;&#237;stico de Verano, A.C.\n ", "name": "oai:sil.org:43023", "is_online": true}, {"url": "http://www.language-archives.org/item/oai:sil.org:54123", "text": "<i>Kut&#250;&#42892;va-yo ka&#42892;vi-yo tu&#817;&#42892;un-yo.</i> Rodrigu&#233;z Flores, Rebeca; Brown de Beatham, Candice. 2012. Instituto Ling&#252;&#237;stico de Verano, A.C.\n ", "name": "oai:sil.org:54123", "is_online": true}, {"url": "http://www.language-archives.org/item/oai:sil.org:13124", "text": "<i>&#191;&#193; x&#238;ni-un nd&#225;a xa&#817;&#42892;&#225; kit&#237; k&#250;&#250;-a?.</i> Brown de Beatham, Candice (consultant). 2009. Instituto Ling&#252;&#237;stico de Verano, A.C.\n ", "name": "oai:sil.org:13124", "is_online": true}, {"url": "http://www.language-archives.org/item/oai:sil.org:53524", "text": "<i>&#191;Nd&#225;a &#237;ya ch&#237;tun?.</i> Brown de Beatham, Candice (consultant); Beatham, Bruce (consultant). 2011. Instituto Ling&#252;&#237;stico de Verano, A.C.\n ", "name": "oai:sil.org:53524", "is_online": true}, {"url": "http://www.language-archives.org/item/oai:sil.org:53525", "text": "<i>K&#225;&#42892;vi-yo nd&#225;a &#243;ra k&#250;&#250;-a.</i> Brown de Beatham, Candice (consultant). 2010. Instituto Ling&#252;&#237;&#173;stico de Verano, A.C.\n ", "name": "oai:sil.org:53525", "is_online": true}, {"url": "http://www.language-archives.org/item/oai:sil.org:53526", "text": "<i>N&#250;mero iin, iin sa&#225; nda&#817;a&#817; iin siento.</i> Brown de Beatham, Candice (consultant). 2011. Instituto Ling&#252;&#237;stico de Verano, A.C.\n ", "name": "oai:sil.org:53526", "is_online": true}, {"url": "http://www.language-archives.org/item/oai:sil.org:53531", "text": "<i>&#191;&#193; x&#238;ni-un nd&#225;a xa&#817;&#42892;&#225; kit&#237; k&#250;&#250;-a?.</i> Brown de Beatham, Candice (consultant). 2010. Instituto Ling&#252;&#237;stico de Verano, A.C.\n ", "name": "oai:sil.org:53531", "is_online": true}, {"url": "http://www.language-archives.org/item/oai:sil.org:53532", "text": "<i>Tu&#817;&#42892;un na&#817; &#241;uu Ki&#817;yaa x&#237;&#42892;in na&#817; xiyo oeste &#241;uu Sku&#237;ya.</i> Brown de Beatham, Candice (consultant); Beatham, Bruce (consultant). 2010. Instituto Ling&#252;&#237;stico de Verano, A.C.\n ", "name": "oai:sil.org:53532", "is_online": true}, {"url": "http://www.language-archives.org/item/oai:sil.org:59733", "text": "<i>Burru l&#237;ndo.</i> Beatham, Candice; Rodrigu&#233;z, Fidela (speaker); Rodrigu&#233;z, Rebeca (speaker). 2014. Instituto Ling&#252;&#237;stico de Verano, A.C.\n ", "name": "oai:sil.org:59733", "is_online": true}, {"url": "http://www.language-archives.org/item/oai:sil.org:51038", "text": "<i>So&#42892;o k&#225;&#225; xa&#817;&#42892;&#462; nu&#817;jn&#464; ntsia&#817;a&#817; xa&#817;a&#817; nt&#237;&#237;-an xi&#817;t&#462;.</i> Rivera Rodr&#237;guez, C&#233;sar; Mendoza Salvador, Socorro; Beatham, Bruce; Brown de Beatham, Candice. 2012. Instituto Ling&#252;&#237;stico de Verano, A.C.\n ", "name": "oai:sil.org:51038", "is_online": true}, {"url": "http://www.language-archives.org/item/oai:sil.org:53641", "text": "<i>Color &#241;a&#817;&#42892;a x&#237;xi-yo.</i> Beatham, Candice (consultant); Mendoza Rodrigu&#233;z, Esther; Rodrigu&#233;z Flores, Rebeca. 2011. Instituto Ling&#252;&#237;stico de Verano, A.C.\n ", "name": "oai:sil.org:53641", "is_online": true}, {"url": "http://www.language-archives.org/item/oai:sil.org:60441", "text": "<i>N&#250;mero iin, iin sa&#225; nta&#817;a&#817; iin ciento.</i> Brown de Beatham, Candice. 10-2014. Instituto Ling&#252;&#237;stico de Verano, A.C.\n ", "name": "oai:sil.org:60441", "is_online": true}, {"url": "http://www.language-archives.org/item/oai:sil.org:59842", "text": "<i>K&#225;&#42892;vi-yo nt&#225;a hora k&#250;&#250;-a.</i> Beatham, Candice. 2014. Instituto Ling&#252;&#237;stico de Verano, A.C.\n ", "name": "oai:sil.org:59842", "is_online": true}, {"url": "http://www.language-archives.org/item/oai:sil.org:12846", "text": "<i>N&#250;mero iin, iin sa&#225; nda&#817;a&#817; iin siento.</i> Brown de Beatham, Candice (consultant). 2009. Instituto Ling&#252;&#237;stico de Verano, A.C.\n ", "name": "oai:sil.org:12846"}, {"url": "http://www.language-archives.org/item/oai:sil.org:59747", "text": "<i>Ich&#237; nu&#817;n&#237; na&#817;xa x&#225;a&#817;-&#241;a ntuu-&#241;a xi&#817;t&#225;.</i> Beatham, Candice. 2014. Instituto Ling&#252;&#237;stico de Verano, A.C.\n ", "name": "oai:sil.org:59747", "is_online": true}, {"url": "http://www.language-archives.org/item/oai:sil.org:59748", "text": "<i>&#191;Nt&#225;a &#237;ya ch&#237;tun?.</i> Brown de Beatham, Candice; Beatham, Bruce. 2014. Instituto Ling&#252;&#237;stico de Verano, A.C.\n ", "name": "oai:sil.org:59748", "is_online": true}, {"url": "http://www.language-archives.org/item/oai:sil.org:59848", "text": "<i>Color &#241;a&#817;&#42892;a x&#237;xi-yo.</i> Beatham, Candice; Mendoza Rodrigu&#233;z, Esther; Rodrigu&#233;z Flores, Rebeca. 2014. Instituto Ling&#252;&#237;stico de Verano, A.C.\n ", "name": "oai:sil.org:59848", "is_online": true}, {"url": "http://www.language-archives.org/item/oai:sil.org:53352", "text": "<i>&#191;&#193; x&#238;ni-un nd&#225;a ndo&#42892;&#243; kit&#237; k&#250;&#250;-a?.</i> Brown de Beatham, Candice (consultant). 2011. Instituto Ling&#252;&#237;stico de Verano, A.C.\n ", "name": "oai:sil.org:53352", "is_online": true}, {"url": "http://www.language-archives.org/item/oai:sil.org:51054", "text": "<i>Ki&#817;ts&#464; n&#225;&#42892;nu x&#237;&#42892;in ki&#817;ts&#464; v&#225;l&#237;.</i> Beatham, Bruce; Beatham, Candice; Rivera Rodr&#237;guez, C&#233;sar; Mendoza, Socorro. 2012. Instituto Ling&#252;&#237;stico de Verano, A.C.\n ", "name": "oai:sil.org:51054", "is_online": true}, {"url": "http://www.language-archives.org/item/oai:sil.org:51058", "text": "<i>&#191;Ntsi&#225;&#225; &#237;yo ch&#250;tu?.</i> Rivera Rodr&#237;guez, C&#233;sar; Beatham, Bruce; Brown de Beatham, Candice; Mendoza Salvador, Socorro. 2012. Instituto Ling&#252;&#237;stico de Verano, A.C.\n ", "name": "oai:sil.org:51058", "is_online": true}, {"url": "http://www.language-archives.org/item/oai:sil.org:59858", "text": "<i>Xi&#817;t&#225; k&#225;&#42892;nu.</i> Brown de Beatham, Candice; Santos P&#233;rez, Fabiola (speaker). 2014. Instituto Ling&#252;&#237;stico de Verano, A.C.\n ", "name": "oai:sil.org:59858", "is_online": true}, {"url": "http://www.language-archives.org/item/oai:sil.org:51059", "text": "<i>N&#250;mero iin ntsia&#817;a&#817; iin ciento.</i> Rivera Rodr&#237;guez, C&#233;sar; Mendoza Salvador, Socorro; Beatham, Bruce; Brown de Beatham, Candice. 2012. Instituto Ling&#252;&#237;stico de Verano, A.C.\n ", "name": "oai:sil.org:51059", "is_online": true}, {"url": "http://www.language-archives.org/item/oai:sil.org:55360", "text": "<i>&#209;a&#817; koo-yo  &#209;a&#817; &#237;yo-yo  &#209;a&#817; ni&#817;xi&#817;yo-yo.</i> Brown de Beatham, Candice; Ram&#237;rez Flores, Esperanza (speaker). 2012. Instituto Ling&#252;&#237;stico de Verano, A.C.\n ", "name": "oai:sil.org:55360", "is_online": true}, {"url": "http://www.language-archives.org/item/oai:sil.org:51061", "text": "<i>&#209;a&#817;&#42892;a nd&#243;&#42892;o-e x&#237;&#42892;in &#241;a&#817;&#42892;a k&#237;xa na&#817; yiv&#464;.</i> Rivera Rodr&#237;guez, C&#233;sar; Mendoza Salvador, Socorro; Beatham, Bruce; Brown de Beatham, Candice. 2012. Instituto Ling&#252;&#237;stico de Verano, A.C.\n ", "name": "oai:sil.org:51061", "is_online": true}, {"url": "http://www.language-archives.org/item/oai:sil.org:51063", "text": "<i>Burru ntivi.</i> Rivera Rodr&#237;guez, C&#233;sar; Mendoza Salvador, Socorro; Rodrigu&#233;z Flores, Fidela; Rodrigu&#233;z Flores, Rebeca; Beatham, Bruce; Brown de Beatham, Candice. 2012. Instituto Ling&#252;&#237;stico de Verano, A.C.\n ", "name": "oai:sil.org:51063", "is_online": true}, {"url": "http://www.language-archives.org/item/oai:sil.org:41464", "text": "<i>Kut&#250;&#42892;va-yo ka&#42892;vi-yo tu&#817;&#42892;un-yo.</i> Rodrigu&#233;z Flores, Rebeca; Brown de Beatham, Candice. 2009. Instituto Ling&#252;&#237;stico de Verano, A.C.\n ", "name": "oai:sil.org:41464", "is_online": true}, {"url": "http://www.language-archives.org/item/oai:sil.org:51066", "text": "<i>&#191;&#193; x&#237;ni-un ntsi&#225;&#225; nto&#42892;&#466; ki&#817;ts&#464; y&#225;&#225;?.</i> Rivera Rodr&#237;guez, C&#233;sar; Mendoza Salvador, Socorro; Beatham, Bruce; Brown de Beatham, Candice. 2012. Instituto Ling&#252;&#237;stico de Verano, A.C.\n ", "name": "oai:sil.org:51066", "is_online": true}, {"url": "http://www.language-archives.org/item/oai:sil.org:55267", "text": "<i>Tu&#817;&#42892;un na&#817; &#241;uu Ki&#817;yaa x&#237;&#42892;in na&#817; xiyo oeste &#241;uu Sku&#237;ya.</i> Brown de Beatham, Candice (consultant); Beatham, Bruce (consultant). 2012. Instituto Ling&#252;&#237;stico de Verano, A.C.\n ", "name": "oai:sil.org:55267", "is_online": true}, {"url": "http://www.language-archives.org/item/oai:sil.org:59867", "text": "<i>&#191;&#193; x&#237;ni-un nt&#225;a xa&#817;&#42892;&#225; kit&#237; k&#250;&#250;-a?.</i> Beatham, Candice. 2014. Instituto Ling&#252;&#237;stico de Verano, A.C.\n ", "name": "oai:sil.org:59867", "is_online": true}, {"url": "http://www.language-archives.org/item/oai:sil.org:59871", "text": "<i>Peque&#241;o Diccionario Ilustrado.</i> Beatham, Candice; Beatham, Bruce. 2014. Instituto Ling&#252;&#237;stico de Verano, A.C.\n ", "name": "oai:sil.org:59871", "is_online": true}, {"url": "http://www.language-archives.org/item/oai:sil.org:51075", "text": "<i>&#191;&#193; x&#237;ni-un ntsi&#225;&#225; xa&#817;&#42892;&#462; ki&#817;ts&#464; y&#225;&#225;?.</i> Rivera Rodr&#237;guez, C&#233;sar; Mendoza Salvador, Socorro; Beatham, Bruce; Brown de Beatham, Candice. 2012. Instituto Ling&#252;&#237;stico de Verano, A.C.\n ", "name": "oai:sil.org:51075", "is_online": true}, {"url": "http://www.language-archives.org/item/oai:sil.org:12681", "text": "<i>K&#225;&#42892;vi-yo nd&#225;a &#243;ra k&#250;&#250;-a.</i> Brown de Beatham, Candice (consultant). 2009. Instituto Ling&#252;&#237;stico de Verano, A.C.\n ", "name": "oai:sil.org:12681", "is_online": true}, {"url": "http://www.language-archives.org/item/oai:sil.org:13181", "text": "<i>Tu&#817;&#42892;un na&#817; &#241;uu Ki&#817;yaa x&#237;&#42892;in na&#817; xiyo oeste &#241;uu Sku&#237;ya.</i> Brown de Beatham, Candice (consultant); Beatham, Bruce (consultant). 2009. Instituto Ling&#252;&#237;stico de Verano, A.C.\n ", "name": "oai:sil.org:13181", "is_online": true}, {"url": "http://www.language-archives.org/item/oai:sil.org:40781", "text": "<i>K&#225;&#42892;vi-yo tu&#817;&#42892;un-yo.</i> Beatham, Candice (consultant). 2011. Instituto Ling&#252;&#237;stico de Verano, A.C.\n ", "name": "oai:sil.org:40781", "is_online": true}, {"url": "http://www.language-archives.org/item/oai:sil.org:40782", "text": "<i>Burru l&#237;ndo.</i> Beatham, Candice (consultant); Rodrigu&#233;z Flores, Fidela (speaker); Rodrigu&#233;z Flores, Rebeca (speaker). 2011. Instituto Ling&#252;&#237;stico de Verano.\n ", "name": "oai:sil.org:40782", "is_online": true}, {"url": "http://www.language-archives.org/item/oai:sil.org:40783", "text": "<i>Leso x&#237; &#42892;in &#241;u&#817;m&#225; tu&#817;&#250;n.</i> Beatham, Bruce (consultant); Flores Rodrigu&#233;z, Sergio (speaker); Flores Rodrigu&#233;z, Margarito (speaker); Beatham, Candice (consultant). 2009. Instituto Ling&#252;&#237;stico de Verano, A.C.\n ", "name": "oai:sil.org:40783", "is_online": true}, {"url": "http://www.language-archives.org/item/oai:sil.org:40784", "text": "<i>Ich&#237; nu&#817;n&#237; na&#817;xa x&#225;a&#817;-&#241;a nduu-&#241;a xi&#817;t&#225;.</i> Beatham, Candice (consultant). 2011. Instituto Ling&#252;&#237;stico de Verano.\n ", "name": "oai:sil.org:40784", "is_online": true}, {"url": "http://www.language-archives.org/item/oai:sil.org:42984", "text": "<i>Iin ndiux&#237; t&#237; va&#817;&#42892;a k&#225;ch&#237;&#241;u k&#250;&#250;-ri.</i> Brown de Beatham, Candice; Melo Rend&#243;n, Faustina (speaker). 2012. Instituto Ling&#252;&#237;&#173;stico de Verano, A.C.\n ", "name": "oai:sil.org:42984", "is_online": true}, {"url": "http://www.language-archives.org/item/oai:sil.org:40785", "text": "<i>Color &#241;a&#817;&#42892;a x&#237;xi-yo.</i> Beatham, Candice (consultant); Mendoza Rodrigu&#233;z, Esther; Rodrigu&#233;z Flores, Rebeca. 2009. Instituto Ling&#252;&#237;stico de Verano, A.C.\n ", "name": "oai:sil.org:40785", "is_online": true}, {"url": "http://www.language-archives.org/item/oai:sil.org:59888", "text": "<i>&#191;&#193; x&#237;ni-un nt&#225;a nto&#42892;&#243; kit&#237; k&#250;&#250;-a?.</i> Brown de Beatham, Candice. 2014. Instituto Ling&#252;&#237;stico de Verano, A.C.\n ", "name": "oai:sil.org:59888", "is_online": true}, {"url": "http://www.language-archives.org/item/oai:sil.org:59889", "text": "<i>&#209;a&#817; koo-yo &#209;a&#817; &#237;yo-yo &#209;a&#817; ni&#817;xi&#817;yo-yo.</i> Brown de Beatham, Candice; Ram&#237;rez Flores, Esperanza (speaker). 2014. Instituto Ling&#252;&#237;stico de Verano, A.C.\n ", "name": "oai:sil.org:59889", "is_online": true}, {"url": "http://www.language-archives.org/item/oai:sil.org:54792", "text": "<i>Xi&#817;t&#225; k&#225;&#42892;nu.</i> Brown de Beatham, Candice; Santos P&#233;rez, Fabiola (speaker). 2012. Instituto Ling&#252;&#237;stico de Verano, A.C.\n ", "name": "oai:sil.org:54792", "is_online": true}, {"url": "http://www.language-archives.org/item/oai:sil.org:51093", "text": "<i>N&#225; ka&#42892;v&#237;-e tu&#817;&#42892;un-e.</i> Rivera Rodr&#237;guez, C&#233;sar; Mendoza Salvador, Socorro; Beatham, Bruce; Brown de Beatham, Candice. 2012. Instituto Ling&#252;&#237;stico de Verano, A.C.\n ", "name": "oai:sil.org:51093", "is_online": true}, {"url": "http://www.language-archives.org/item/oai:sil.org:40794", "text": "<i>Kit&#237; n&#225;&#42892;nu x&#237;&#42892;in kit&#237; v&#225;l&#237;.</i> Beatham, Candice (consultant); Mendoza Rodrigu&#233;z, Esther; Rodrigu&#233;z Flores, Rebeca. 2009. Instituto Ling&#252;&#237;stico de Verano, A.C.\n ", "name": "oai:sil.org:40794", "is_online": true}, {"url": "http://www.language-archives.org/item/oai:sil.org:59794", "text": "<i>Iin ntiux&#237; t&#237; va&#817;&#42892;a k&#225;ch&#237;&#241;u k&#250;&#250;-ri.</i> Brown de Beatham, Candice; Melo Rend&#243;n, Faustina (speaker). 2014. Instituto Ling&#252;&#237;stico de Verano, A.C.\n ", "name": "oai:sil.org:59794", "is_online": true}, {"url": "http://www.language-archives.org/item/oai:sil.org:57595", "text": "<i>Leso x&#237;&#42892;in &#241;u&#817;m&#225; tu&#817;&#250;n.</i> Beatham, Bruce (consultant); Flores Rodrigu&#233;z, Sergio (speaker); Flores Rodrigu&#233;z, Margarito (speaker); Beatham, Candice (consultant). 2011. Instituto Ling&#252;&#237;stico de Verano, A.C.\n ", "name": "oai:sil.org:57595", "is_online": true}, {"url": "http://www.language-archives.org/item/oai:cla.berkeley.edu:deAvila.001", "text": "<i>[Coicoyan Mixtec notes and transcriptions].</i> de Avila, Alejandro (researcher); M&#233;ndez, Sergio (consultant); Flores, Celso (consultant). 1996. California Language Archive.\n ", "name": "oai:cla.berkeley.edu:deAvila.001"}, {"url": "http://www.language-archives.org/item/oai:ethnologue.com:jmx", "text": "<i>Mixtec, Western Juxtlahuaca: a language of Mexico.</i> n.a. 2013. SIL International.\n ", "name": "oai:ethnologue.com:jmx", "is_online": true}, {"url": "http://www.language-archives.org/item/oai:linguistlist.org:lang_jmx", "text": "<i>LINGUIST List Resources for Mixtec, Western Juxtlahuaca.</i> Damir Cavar, Director of Linguist List (editor); Malgorzata E. Cavar, Director of Linguist List (editor). 2016-05-21. The LINGUIST List (www.linguistlist.org).\n ", "name": "oai:linguistlist.org:lang_jmx", "is_online": true}]}, "Language descriptions": {"count": 1, "resources": [{"url": "http://www.language-archives.org/item/oai:glottolog.org:west2643", "text": "<i>Glottolog 2.7 Resources for Western Juxtlahuaca Mixtec.</i> n.a. 2015. Max Planck Institute for the Science of Human History.\n ", "name": "oai:glottolog.org:west2643", "is_online": true}]}}}