{"url": "http://www.language-archives.org/language/kbu", "code": "kbu", "coords": ["25.292", "69.691"], "name": "Kabutra", "resources": {"Other resources about the language": {"count": 1, "resources": [{"url": "http://www.language-archives.org/item/oai:ethnologue.com:kbu", "text": "<i>Kabutra: a language of Pakistan.</i> n.a. 2013. SIL International.\n ", "name": "oai:ethnologue.com:kbu", "is_online": true}]}, "Language descriptions": {"count": 1, "resources": [{"url": "http://www.language-archives.org/item/oai:glottolog.org:kabu1254", "text": "<i>Glottolog 2.6 Resources for Kabutra.</i> n.a. 2015. Max Planck Institute for the Science of Human History.\n ", "name": "oai:glottolog.org:kabu1254", "is_online": true}]}}}