{"url": "http://www.language-archives.org/language/mcp", "code": "mcp", "coords": ["4.15471", "13.0789"], "name": "Makaa", "resources": {"Lexical resources": {"count": 1, "resources": [{"url": "http://www.language-archives.org/item/oai:sil.org:32307", "text": "<i>Lexique m&#477;ka&#225;-fran&#231;ais.</i> Heath, Daniel (editor). 1989. Soci&#233;t&#233; Internationale de Linguistique.\n ", "name": "oai:sil.org:32307"}]}, "Other resources about the language": {"count": 32, "resources": [{"url": "http://www.language-archives.org/item/oai:refdb.wals.info:4763", "text": "<i>Makaa (A83).</i> Heath, Teresa. 2003. The Bantu Languages.\n ", "name": "oai:refdb.wals.info:4763", "is_online": true}, {"url": "http://www.language-archives.org/item/oai:sil.org:33101", "text": "<i>Textes selectionn&#233;s.</i> Heath, Daniel; Heath, Teresa. 1997. Minist&#232;re de la Recherche Scientifique et Technique and Soci&#233;t&#233; Internationale de Linguistique.\n ", "name": "oai:sil.org:33101"}, {"url": "http://www.language-archives.org/item/oai:sil.org:47602", "text": "<i>N&#601;c&#233; j&#237; sh&#233; m&#601;&#769; d&#769;&#649;&#769; b&#601; n&#601; mishw&#243;&#243;mb&#250; y&#237;.</i> Kouamb, Alexis (editor); Hegetschweiler, Elisabeth (illustrator); Heath, Daniel (editor). 1999. Centre de Litt&#233;rature en langue mekaa.\n ", "name": "oai:sil.org:47602", "is_online": true}, {"url": "http://www.language-archives.org/item/oai:sil.org:3307", "text": "<i>Relative clauses in m&#477;kaa.</i> Heath, Daniel; Heath, Teresa. 1984. Journal of West African Languages.\n ", "name": "oai:sil.org:3307", "is_online": true}, {"url": "http://www.language-archives.org/item/oai:sil.org:53409", "text": "<i>M&#477;bya&#331; m&#477;&#769; m&#477;&#769;bwas m&#477;&#769; &#237;famb&#477;&#769;.</i> Mbanji, Bawe Ernest (illustrator). 1992. ANACLAC/SIL.\n ", "name": "oai:sil.org:53409", "is_online": true}, {"url": "http://www.language-archives.org/item/oai:sil.org:32913", "text": "<i>M&#601;c&#251;&#331; m&#225; m&#601;bwas.</i> Mindola, J&#233;r&#233;mie (editor). 2002. Comit&#233; de langue M&#601;ka&#225;.\n ", "name": "oai:sil.org:32913"}, {"url": "http://www.language-archives.org/item/oai:sil.org:50317", "text": "<i>Mbu 1995.</i> Mbanji, Bawe Ernest (illustrator). 1995. Centre de litt&#233;rature en langue makaa.\n ", "name": "oai:sil.org:50317"}, {"url": "http://www.language-archives.org/item/oai:sil.org:8819", "text": "<i>Tone in the Makaa associative construction.</i> Heath, Daniel. 1991. SIL International Publications in Linguistics 102.\n ", "name": "oai:sil.org:8819", "is_online": true}, {"url": "http://www.language-archives.org/item/oai:sil.org:33021", "text": "<i>Sh&#233; &#331;g&#477;&#769; j&#237;&#237;g&#649;&#769;l&#477; l&#243;&#243;l&#477;.</i> Boer, Truus (editor); Nkoasse Claire (editor); Phillips, Elisabeth (editor). 1990. Soci&#233;t&#233; Internationale de Linguistique.\n ", "name": "oai:sil.org:33021"}, {"url": "http://www.language-archives.org/item/oai:sil.org:33022", "text": "<i>Manuel pour lire et &#233;crire la langue m&#601;kaa.</i> Ankanda Essola, Boniface (editor); Kouamb, Alexis (editor); Ze, Saturnin (editor). 1996. Soci&#233;t&#233; Internationale de Linguistique.\n ", "name": "oai:sil.org:33022"}, {"url": "http://www.language-archives.org/item/oai:sil.org:33025", "text": "<i>Mikaan&#477;&#769; m&#237; m&#477;ka&#225; 1.</i> Centre de litt&#233;rature en langue m&#477;kaa (compiler). 1996. Soci&#233;t&#233; Internationale de Linguistique.\n ", "name": "oai:sil.org:33025"}, {"url": "http://www.language-archives.org/item/oai:sil.org:33426", "text": "<i>Multilingual Cameroon: Reader in Cameroonian languages.</i> Gfeller, Elisabeth (editor); Mbanji, Bawe Ernest (illustrator). 1990. Soci&#233;t&#233; Internationale de Linguistique.\n ", "name": "oai:sil.org:33426"}, {"url": "http://www.language-archives.org/item/oai:sil.org:33327", "text": "<i>N&#477;c&#233; j&#237; sh&#233; m&#477;&#769; d&#649; b&#477; n&#477; mishw&#243;&#243;mb&#250;.</i> Heath, Daniel; Kouamb, Alexis. 1989. Soci&#233;t&#233; Internationale de Linguistique.\n ", "name": "oai:sil.org:33327"}, {"url": "http://www.language-archives.org/item/oai:sil.org:47639", "text": "<i>Mikanda mi m&#233;kaa&#224; 1.</i> Mbeul, Martin; Ze, Saturnin. 1996. Soci&#233;t&#233; Internationale de Linguistique.\n ", "name": "oai:sil.org:47639", "is_online": true}, {"url": "http://www.language-archives.org/item/oai:sil.org:33240", "text": "<i>Manuel pour lire et &#233;crire la langue m&#477;ka&#225;.</i> Heath, Daniel (editor). 1985. Soci&#233;t&#233; Internationale de Linguistique.\n ", "name": "oai:sil.org:33240"}, {"url": "http://www.language-archives.org/item/oai:sil.org:47662", "text": "<i>Un projet d'alphab&#233;tisation en langue mekaa dans le Consistoire Nkol Mvolan.</i> Heeley, Matthew. 2000. SIL Cameroon.\n ", "name": "oai:sil.org:47662", "is_online": true}, {"url": "http://www.language-archives.org/item/oai:sil.org:33170", "text": "<i>Mbi&#237; bw&#243; d&#649;&#769; s&#226; m&#477;ny&#225;&#331; m&#477;&#769; soja y&#237;.</i> Ankanda Essola, Boniface (translator). 2000. Centre de Litt&#233;rature en Langue Mekaa.\n ", "name": "oai:sil.org:33170"}, {"url": "http://www.language-archives.org/item/oai:sil.org:47670", "text": "<i>A study of reader interest among the Makaa people of eastern Cameroon.</i> Heeley, Matthew. 2000. SIL Cameroon.\n ", "name": "oai:sil.org:47670", "is_online": true}, {"url": "http://www.language-archives.org/item/oai:sil.org:33074", "text": "<i>La&#331; a mpwo&#331; buud m&#477;kaa.</i> Boer, Truus (editor); Nkoasse Claire (editor). 1992. Soci&#233;t&#233; Internationale de Linguistique.\n ", "name": "oai:sil.org:33074"}, {"url": "http://www.language-archives.org/item/oai:sil.org:33177", "text": "<i>Mikanda m&#237; m&#477;&#769;ka&#225;.</i> Heath, Daniel; Mbeul, Martin; Ze, Saturnin. 1983. Soci&#233;t&#233; Internationale de Linguistique.\n ", "name": "oai:sil.org:33177"}, {"url": "http://www.language-archives.org/item/oai:sil.org:5278", "text": "<i>SALT 98: a short-term literacy team in Cameroon.</i> Clayton, Fiona; Hunt, Jason; Hunt, Ulrike; Zandbergen, Alies. 2000. Notes on Literacy.\n ", "name": "oai:sil.org:5278"}, {"url": "http://www.language-archives.org/item/oai:sil.org:33378", "text": "<i>M&#477;bya&#331; m&#477;&#769; m&#477;&#769;bwas m&#477;&#769; &#237;famb&#477;&#769;: Mbi&#237; b&#477;&#769; d&#649;&#769; b&#477;la n&#477; nw&#477; y&#237;.</i> Comit&#233; de langue m&#477;kaa (translator). 1992. Association Nationale de Comit&#233;s de Langues Camerounaises.\n ", "name": "oai:sil.org:33378"}, {"url": "http://www.language-archives.org/item/oai:sil.org:33379", "text": "<i>K&#225;l&#225; tow m&#477;&#769; c&#603;&#603;l b&#477; nkweny.</i> White, Paul. 1999. Comit&#233; de Langue Mekaa.\n ", "name": "oai:sil.org:33379"}, {"url": "http://www.language-archives.org/item/oai:sil.org:47680", "text": "<i>Makaa Mekhist.</i> Boer, Truus (compiler); Nkoasse, Bessa Claire (compiler). n.d. SIL Cameroon.\n ", "name": "oai:sil.org:47680"}, {"url": "http://www.language-archives.org/item/oai:sil.org:32981", "text": "<i>Sh&#233; m&#596;&#769; j&#237;&#237; m&#596;t&#226;&#331; 2.</i> Ankanda Essola, Boniface (translator). 2002. PROPELCA.\n ", "name": "oai:sil.org:32981"}, {"url": "http://www.language-archives.org/item/oai:sil.org:8584", "text": "<i>Tense and aspect in Makaa.</i> Heath, Daniel. 1991. SIL International Publications in Linguistics 99.\n ", "name": "oai:sil.org:8584", "is_online": true}, {"url": "http://www.language-archives.org/item/oai:sil.org:32986", "text": "<i>Sh&#232; &#331;g&#477; j&#237;&#237;g l&#243;&#807;l&#477; 2 (Syllabaire en langue m&#477;ka&#225; tome 2).</i> Ankanda Essola, Boniface; Boer, Truus; Nkoasse Claire; Phillips, Elisabeth; Berg, Nelis van den. 2003. SIL-Cameroun.\n ", "name": "oai:sil.org:32986"}, {"url": "http://www.language-archives.org/item/oai:sil.org:8693", "text": "<i>Tone in five languages of Cameroon.</i> Anderson, Stephen C. (editor). 1991. SIL International Publications in Linguistics 102.\n ", "name": "oai:sil.org:8693", "is_online": true}, {"url": "http://www.language-archives.org/item/oai:sil.org:2897", "text": "<i>A phonology of the m&#477;kaa language.</i> Heath, Daniel; Heath, Teresa. 1982. Soci&#233;t&#233; Internationale de Linguistique.\n ", "name": "oai:sil.org:2897"}, {"url": "http://www.language-archives.org/item/oai:sil.org:33299", "text": "<i>Z&#601; &#225; d&#601; ibu&#821;l&#250;?.</i> Mendjand, Emmanuel. 2002. Comit&#233; de langue M&#601;ka&#225;.\n ", "name": "oai:sil.org:33299"}, {"url": "http://www.language-archives.org/item/oai:rosettaproject.org:rosettaproject_mcp_book-1", "text": "<i>A Phonology of the Makaa Language.</i> Heath, Daniel; Heath, Teresa. 1982. Societe Internationale de Linguistique.\n ", "name": "oai:rosettaproject.org:rosettaproject_mcp_book-1", "is_online": true}, {"url": "http://www.language-archives.org/item/oai:ethnologue.com:mcp", "text": "<i>Makaa: a language of Cameroon.</i> n.a. 2013. SIL International.\n ", "name": "oai:ethnologue.com:mcp", "is_online": true}]}, "Language descriptions": {"count": 11, "resources": [{"url": "http://www.language-archives.org/item/oai:glottolog.org:maka1304", "text": "<i>Glottolog 2.6 Resources for Makaa.</i> n.a. 2015. Max Planck Institute for the Science of Human History.\n ", "name": "oai:glottolog.org:maka1304", "is_online": true}, {"url": "http://www.language-archives.org/item/oai:phoible.org:mcp", "text": "<i>PHOIBLE Online phonemic inventories for Makaa.</i> n.a. 2014. Max Planck Institute for Evolutionary Anthropology.\n ", "name": "oai:phoible.org:mcp", "is_online": true}, {"url": "http://www.language-archives.org/item/oai:rosettaproject.org:rosettaproject_mcp_ortho-1", "text": "<i>Alphabets of Africa.</i> Hartell, Rhonda L. 1993. BREDA Press.\n ", "name": "oai:rosettaproject.org:rosettaproject_mcp_ortho-1", "is_online": true}, {"url": "http://www.language-archives.org/item/oai:sil.org:1211", "text": "<i>Makaa (A83).</i> Heath, Teresa. 2003. Routledge language family series.\n ", "name": "oai:sil.org:1211"}, {"url": "http://www.language-archives.org/item/oai:sil.org:47595", "text": "<i>Makaa discourse features.</i> Heath, Daniel P.; Heath, Teresa A. 2005. SIL Cameroon.\n ", "name": "oai:sil.org:47595", "is_online": true}, {"url": "http://www.language-archives.org/item/oai:sil.org:47660", "text": "<i>A preliminary grammar sketch of the Makaa noun modifiers and pronouns.</i> Heath, Daniel P.; Heath, Teresa. 1998. SIL Cameroon.\n ", "name": "oai:sil.org:47660", "is_online": true}, {"url": "http://www.language-archives.org/item/oai:sil.org:47661", "text": "<i>A preliminary grammar sketch of the M&#233;kaa noun and verb morphology.</i> Heath, Daniel P.; Heath, Teresa. 1996. SIL Cameroon.\n ", "name": "oai:sil.org:47661", "is_online": true}, {"url": "http://www.language-archives.org/item/oai:sil.org:47916", "text": "<i>Tone in the Makaa associative construction.</i> Heath, Daniel. 1991. SIL.\n ", "name": "oai:sil.org:47916", "is_online": true}, {"url": "http://www.language-archives.org/item/oai:sil.org:47920", "text": "<i>Preposed constituents and discontinuities in Makaa discourse.</i> Heath, Daniel P.; Heath, Teresa A. 1993. Soci&#233;t&#233; Internationale de Linguistique.\n ", "name": "oai:sil.org:47920", "is_online": true}, {"url": "http://www.language-archives.org/item/oai:sil.org:8690", "text": "<i>Preposed constituents and discontinuities in Makaa discourse.</i> Heath, Daniel; Heath, Teresa. 1994. SIL International Publications in Linguistics 119.\n ", "name": "oai:sil.org:8690"}, {"url": "http://www.language-archives.org/item/oai:wals.info:mkz", "text": "<i>WALS Online Resources for Makaa.</i> n.a. 2008. Max Planck Institute for Evolutionary Anthropology.\n ", "name": "oai:wals.info:mkz", "is_online": true}]}}}