{"url": "http://www.language-archives.org/language/mjx", "code": "mjx", "coords": ["26.391", "22.091", "86.656", "88.254"], "name": "Mahali language", "resources": {"Other resources about the language": {"count": 2, "resources": ["<li><span class=\"online_indicator\">ONLINE</span><i>The Santali cluster in Bangladesh: a sociolinguistic survey.</i> Kim, Seung; Kim, Amy. 2010. SIL Electronic Survey Reports 2010-006.\n <a href=\"/item/oai:sil.org:9037\">oai:sil.org:9037</a></li>", "<li><span class=\"online_indicator\">ONLINE</span><i>Mahali: a language of India.</i> n.a. 2013. SIL International.\n <a href=\"/item/oai:ethnologue.com:mjx\">oai:ethnologue.com:mjx</a></li>"]}, "Language descriptions": {"count": 1, "resources": ["<li><span class=\"online_indicator\">ONLINE</span><i>Glottolog 2.6 Resources for Mahali.</i> n.a. 2015. Max Planck Institute for the Science of Human History.\n <a href=\"/item/oai:glottolog.org:maha1291\">oai:glottolog.org:maha1291</a></li>"]}}}