{"url": "http://www.language-archives.org/language/mkn", "code": "mkn", "coords": ["", "-10.12", "-10.375", "123.293"], "name": "Kupang Malay language", "resources": {"Lexical resources": {"count": 1, "resources": [{"url": "http://www.language-archives.org/item/oai:crubadan.org:mkn", "text": "<i>Cr&#250;bad&#225;n language data for Kupang Malay.</i> Kevin Scannell. 2015. The Cr&#250;bad&#225;n Project.\n ", "name": "oai:crubadan.org:mkn", "is_online": true}]}, "Other resources about the language": {"count": 4, "resources": [{"url": "http://www.language-archives.org/item/oai:sil.org:6339", "text": "<i>Developing a role for Kupang Malay: the contemporary politics of an eastern Indonesian creole.</i> Grimes, Barbara Dix; Jacob, June. 2006. Linguistic Society of the Philippines and SIL International.\n ", "name": "oai:sil.org:6339", "is_online": true}, {"url": "http://www.language-archives.org/item/oai:www.mpi.nl:MPI2010190", "text": "<i>Baird_Kalabahi Malay.</i> n.a. 2003. The Language Archive's IMDI portal.\n ", "name": "oai:www.mpi.nl:MPI2010190", "is_online": true}, {"url": "http://www.language-archives.org/item/oai:www.mpi.nl:MPI2010179", "text": "<i>Klamer_Kalabahi Malay.</i> n.a. 2003. The Language Archive's IMDI portal.\n ", "name": "oai:www.mpi.nl:MPI2010179", "is_online": true}, {"url": "http://www.language-archives.org/item/oai:ethnologue.com:mkn", "text": "<i>Malay, Kupang: a language of Indonesia.</i> n.a. 2013. SIL International.\n ", "name": "oai:ethnologue.com:mkn", "is_online": true}]}, "Language descriptions": {"count": 2, "resources": [{"url": "http://www.language-archives.org/item/oai:glottolog.org:kupa1239", "text": "<i>Glottolog 2.6 Resources for Kupang Malay.</i> n.a. 2015. Max Planck Institute for the Science of Human History.\n ", "name": "oai:glottolog.org:kupa1239", "is_online": true}, {"url": "http://www.language-archives.org/item/oai:phoible.org:mkn", "text": "<i>PHOIBLE Online phonemic inventories for Kupang Malay.</i> n.a. 2014. Max Planck Institute for Evolutionary Anthropology.\n ", "name": "oai:phoible.org:mkn", "is_online": true}]}, "Primary texts": {"count": 1, "resources": [{"url": "http://www.language-archives.org/item/oai:rosettaproject.org:rosettaproject_mkn_gen-1", "text": "<i>Malay, Kupang Genesis Translation.</i> The Long Now Foundation. 2001. Artha Wacana Press.\n ", "name": "oai:rosettaproject.org:rosettaproject_mkn_gen-1", "is_online": true}]}}}