{"url": "http://www.language-archives.org/language/mpi", "code": "mpi", "coords": ["12.4609", "14.5833"], "name": "Mpade", "resources": {"Lexical resources": {"count": 1, "resources": [{"url": "http://www.language-archives.org/item/oai:sil.org:47599", "text": "<i>Makary Kotoko provisional lexicon.</i> Allison, Sean (compiler). 1999. SIL Cameroon.\n ", "name": "oai:sil.org:47599", "is_online": true}]}, "Other resources about the language": {"count": 1, "resources": [{"url": "http://www.language-archives.org/item/oai:ethnologue.com:mpi", "text": "<i>Mpade: a language of Cameroon.</i> n.a. 2013. SIL International.\n ", "name": "oai:ethnologue.com:mpi", "is_online": true}]}, "Language descriptions": {"count": 3, "resources": [{"url": "http://www.language-archives.org/item/oai:glottolog.org:mpad1242", "text": "<i>Glottolog 2.6 Resources for Mpade.</i> n.a. 2015. Max Planck Institute for the Science of Human History.\n ", "name": "oai:glottolog.org:mpad1242", "is_online": true}, {"url": "http://www.language-archives.org/item/oai:phoible.org:mpi", "text": "<i>PHOIBLE Online phonemic inventories for Mpade.</i> n.a. 2014. Max Planck Institute for Evolutionary Anthropology.\n ", "name": "oai:phoible.org:mpi", "is_online": true}, {"url": "http://www.language-archives.org/item/oai:sil.org:32321", "text": "<i>Alphabet et orthographe de Kotoko de Makary (mpadi&#821;).</i> Allison, Sean D. 2006. SIL.\n ", "name": "oai:sil.org:32321", "is_online": true}]}}}