{"url": "http://www.language-archives.org/language/mui", "code": "mui", "coords": ["-2.93987", "103.945"], "name": "Musi", "resources": {"Other resources about the language": {"count": 2, "resources": [{"url": "http://www.language-archives.org/item/oai:sil.org:9245", "text": "<i>Malay dialects of the Batanghari river basin (Jambi, Sumatra).</i> Anderbeck, Karl Ronald. 2008. SIL e-Books 6.\n ", "name": "oai:sil.org:9245", "is_online": true}, {"url": "http://www.language-archives.org/item/oai:ethnologue.com:mui", "text": "<i>Musi: a language of Indonesia.</i> n.a. 2013. SIL International.\n ", "name": "oai:ethnologue.com:mui", "is_online": true}]}, "Language descriptions": {"count": 1, "resources": [{"url": "http://www.language-archives.org/item/oai:glottolog.org:musi1241", "text": "<i>Glottolog 2.6 Resources for Musi (Malay).</i> n.a. 2015. Max Planck Institute for the Science of Human History.\n ", "name": "oai:glottolog.org:musi1241", "is_online": true}]}}}