{"url": "http://www.language-archives.org/language/mxf", "code": "mxf", "coords": ["12.768", "12.194", "14.696", "15.023"], "name": "Malgbe language", "resources": {"Lexical resources": {"count": 1, "resources": [{"url": "http://www.language-archives.org/item/oai:rosettaproject.org:rosettaproject_mxf_swadesh-1", "text": "<i>Malgbe Swadesh List.</i> n.a. n.d. The Rosetta Project: A Long Now Foundation Library of Human Language.\n ", "name": "oai:rosettaproject.org:rosettaproject_mxf_swadesh-1", "is_online": true}]}, "Other resources about the language": {"count": 1, "resources": [{"url": "http://www.language-archives.org/item/oai:ethnologue.com:mxf", "text": "<i>Malgbe: a language of Cameroon.</i> n.a. 2013. SIL International.\n ", "name": "oai:ethnologue.com:mxf", "is_online": true}]}, "Language descriptions": {"count": 1, "resources": [{"url": "http://www.language-archives.org/item/oai:glottolog.org:malg1250", "text": "<i>Glottolog 2.6 Resources for Malgbe.</i> n.a. 2015. Max Planck Institute for the Science of Human History.\n ", "name": "oai:glottolog.org:malg1250", "is_online": true}]}}}