{"url": "http://www.language-archives.org/language/mzx", "code": "mzx", "coords": ["2.013", "1.963", "-58.53", "-58.48"], "name": "Mawayana language", "resources": {"Other resources about the language": {"count": 1, "resources": [{"url": "http://www.language-archives.org/item/oai:ethnologue.com:mzx", "text": "<i>Mawayana: a language of Guyana.</i> n.a. 2013. SIL International.\n ", "name": "oai:ethnologue.com:mzx", "is_online": true}]}, "Language descriptions": {"count": 1, "resources": [{"url": "http://www.language-archives.org/item/oai:glottolog.org:mawa1271", "text": "<i>Glottolog 2.6 Resources for Mawayana.</i> n.a. 2015. Max Planck Institute for the Science of Human History.\n ", "name": "oai:glottolog.org:mawa1271", "is_online": true}]}}}