{"url": "http://www.language-archives.org/language/nhh", "code": "nhh", "coords": ["", "", "", ""], "name": "Nahari language", "resources": {"Other resources about the language": {"count": 1, "resources": ["<li><span class=\"online_indicator\">ONLINE</span><i>Nahari: a language of India.</i> n.a. 2013. SIL International.\n <a href=\"/item/oai:ethnologue.com:nhh\">oai:ethnologue.com:nhh</a></li>"]}, "Language descriptions": {"count": 1, "resources": ["<li><span class=\"online_indicator\">ONLINE</span><i>Glottolog 2.6 Resources for Nahari.</i> n.a. 2015. Max Planck Institute for the Science of Human History.\n <a href=\"/item/oai:glottolog.org:naha1262\">oai:glottolog.org:naha1262</a></li>"]}}}