{"url": "http://www.language-archives.org/language/pdt", "code": "pdt", "coords": ["12.0466", "-81.3525"], "name": "Plautdietsch", "resources": {"Lexical resources": {"count": 1, "resources": [{"url": "http://www.language-archives.org/item/oai:crubadan.org:pdt", "text": "<i>Cr&#250;bad&#225;n language data for Plautdietsch.</i> Kevin Scannell. 2015. The Cr&#250;bad&#225;n Project.\n ", "name": "oai:crubadan.org:pdt", "is_online": true}]}, "Other resources about the language": {"count": 5, "resources": [{"url": "http://www.language-archives.org/item/oai:sil.org:16106", "text": "<i>Wie r&#228;den en l&#228;sen plautdietsch.</i> Fast, Mary; Fast, Peter W. 1982. Summer Institute of Linguistics.\n ", "name": "oai:sil.org:16106"}, {"url": "http://www.language-archives.org/item/oai:sil.org:3129", "text": "<i>Compound words: Plautdietsch.</i> Fast, Peter W. 1985. sn.\n ", "name": "oai:sil.org:3129"}, {"url": "http://www.language-archives.org/item/oai:sil.org:16167", "text": "<i>Wie r&#228;den en l&#228;sen plautdietsch.</i> Fast, Peter W. 1987. Kindred Press.\n ", "name": "oai:sil.org:16167"}, {"url": "http://www.language-archives.org/item/oai:ethnologue.com:pdt", "text": "<i>Plautdietsch: a language of Canada.</i> n.a. 2013. SIL International.\n ", "name": "oai:ethnologue.com:pdt", "is_online": true}, {"url": "http://www.language-archives.org/item/oai:linguistlist.org:lang_pdt", "text": "<i>LINGUIST List Resources for Plautdietsch.</i> Damir Cavar, Director of Linguist List (editor); Malgorzata E. Cavar, Director of Linguist List (editor). 2015-12-22. The LINGUIST List (www.linguistlist.org).\n ", "name": "oai:linguistlist.org:lang_pdt", "is_online": true}]}, "Language descriptions": {"count": 1, "resources": [{"url": "http://www.language-archives.org/item/oai:glottolog.org:plau1238", "text": "<i>Glottolog 2.6 Resources for Plautdietsch.</i> n.a. 2014. Max Planck Institute for the Science of Human History.\n ", "name": "oai:glottolog.org:plau1238", "is_online": true}]}}}