{"url": "http://www.language-archives.org/language/rji", "code": "rji", "coords": ["28.83", "28.545", "80.878", "81.647"], "name": "Raji language", "resources": {"Other resources about the language": {"count": 3, "resources": [{"url": "http://www.language-archives.org/item/oai:refdb.wals.info:7105", "text": "<i>Raji.</i> Sharma, Devi&#175;datta D. 1990. Tribal languages of Uttarakhand 2.\n ", "name": "oai:refdb.wals.info:7105", "is_online": true}, {"url": "http://www.language-archives.org/item/oai:ethnologue.com:rji", "text": "<i>Raji: a language of Nepal.</i> n.a. 2013. SIL International.\n ", "name": "oai:ethnologue.com:rji", "is_online": true}, {"url": "http://www.language-archives.org/item/oai:linguistlist.org:lang_rji", "text": "<i>LINGUIST List Resources for Raji.</i> Damir Cavar, Director of Linguist List (editor); Malgorzata E. Cavar, Director of Linguist List (editor). 2015-12-22. The LINGUIST List (www.linguistlist.org).\n ", "name": "oai:linguistlist.org:lang_rji", "is_online": true}]}, "Language descriptions": {"count": 2, "resources": [{"url": "http://www.language-archives.org/item/oai:glottolog.org:raji1240", "text": "<i>Glottolog 2.6 Resources for Raji.</i> n.a. 2015. Max Planck Institute for the Science of Human History.\n ", "name": "oai:glottolog.org:raji1240", "is_online": true}, {"url": "http://www.language-archives.org/item/oai:wals.info:rji", "text": "<i>WALS Online Resources for Raji.</i> n.a. 2013. Max Planck Institute for Evolutionary Anthropology.\n ", "name": "oai:wals.info:rji", "is_online": true}]}}}