{"url": "http://www.language-archives.org/language/rwk", "code": "rwk", "coords": ["-3.231", "-3.6", "36.593", "36.944"], "name": "Rwa language", "resources": {"Other resources about the language": {"count": 1, "resources": [{"url": "http://www.language-archives.org/item/oai:ethnologue.com:rwk", "text": "<i>Rwa: a language of Tanzania.</i> n.a. 2013. SIL International.\n ", "name": "oai:ethnologue.com:rwk", "is_online": true}]}, "Language descriptions": {"count": 1, "resources": [{"url": "http://www.language-archives.org/item/oai:glottolog.org:rwaa1238", "text": "<i>Glottolog 2.6 Resources for Rwa.</i> n.a. 2015. Max Planck Institute for the Science of Human History.\n ", "name": "oai:glottolog.org:rwaa1238", "is_online": true}]}}}