{"url": "http://www.language-archives.org/language/wag", "code": "wag", "coords": ["-10.2897", "150.398"], "name": "Wa'ema", "resources": {"Other resources about the language": {"count": 1, "resources": [{"url": "http://www.language-archives.org/item/oai:ethnologue.com:wag", "text": "<i>Wa'ema: a language of Papua New Guinea.</i> n.a. 2013. SIL International.\n ", "name": "oai:ethnologue.com:wag", "is_online": true}]}, "Language descriptions": {"count": 1, "resources": [{"url": "http://www.language-archives.org/item/oai:glottolog.org:waem1237", "text": "<i>Glottolog 2.6 Resources for Wa'ema.</i> n.a. 2015. Max Planck Institute for the Science of Human History.\n ", "name": "oai:glottolog.org:waem1237", "is_online": true}]}}}