{"url": "http://www.language-archives.org/language/xyt", "code": "xyt", "coords": ["", "", "", ""], "name": "Mayi-Thakurti language", "resources": {"Other resources about the language": {"count": 1, "resources": [{"url": "http://www.language-archives.org/item/oai:ethnologue.com:xyt", "text": "<i>Mayi-Thakurti: a language of Australia.</i> n.a. 2013. SIL International.\n ", "name": "oai:ethnologue.com:xyt", "is_online": true}]}, "Primary texts": {"count": 2, "resources": [{"url": "http://www.language-archives.org/item/oai:paradisec.org.au:GB28-001", "text": "<i>Wunumara vocabulary, sentences and discussion.</i> Gavan Breen (compiler). 1975. Pacific And Regional Archive for Digital Sources in Endangered Cultures (PARADISEC).\n ", "name": "oai:paradisec.org.au:GB28-001", "is_online": true}, {"url": "http://www.language-archives.org/item/oai:paradisec.org.au:GB29-001", "text": "<i>Mayi-Thakurti vocabulary and elicitation sentences.</i> Gavan Breen (compiler). 1975. Pacific And Regional Archive for Digital Sources in Endangered Cultures (PARADISEC).\n ", "name": "oai:paradisec.org.au:GB29-001", "is_online": true}]}}}