{"url": "http://www.language-archives.org/language/dyd", "code": "dyd", "coords": ["-17.727", "-18.037", "122.171", "122.645"], "name": "Dyugun language", "resources": {"Other resources about the language": {"count": 1, "resources": ["<li><span class=\"online_indicator\">ONLINE</span><i>Dyugun: a language of Australia.</i> n.a. 2013. SIL International.\n <a href=\"/item/oai:ethnologue.com:dyd\">oai:ethnologue.com:dyd</a></li>"]}, "Language descriptions": {"count": 1, "resources": ["<li><span class=\"online_indicator\">ONLINE</span><i>Glottolog 2.6 Resources for Dyugun.</i> n.a. 2015. Max Planck Institute for the Science of Human History.\n <a href=\"/item/oai:glottolog.org:dyug1238\">oai:glottolog.org:dyug1238</a></li>"]}}}