{"url": "http://www.language-archives.org/language/naa", "code": "naa", "coords": ["", "", "", ""], "name": "Namla language", "resources": {"Other resources about the language": {"count": 1, "resources": ["<li><span class=\"online_indicator\">ONLINE</span><i>Namla: a language of Indonesia.</i> n.a. 2013. SIL International.\n <a href=\"/item/oai:ethnologue.com:naa\">oai:ethnologue.com:naa</a></li>"]}, "Language descriptions": {"count": 1, "resources": ["<li><span class=\"online_indicator\">ONLINE</span><i>Glottolog 2.6 Resources for Namla.</i> n.a. 2015. Max Planck Institute for the Science of Human History.\n <a href=\"/item/oai:glottolog.org:naml1240\">oai:glottolog.org:naml1240</a></li>"]}}}