{"url": "http://www.language-archives.org/language/trl", "code": "trl", "coords": ["", "", "", ""], "name": "Traveller Scottish language", "resources": {"Other resources about the language": {"count": 2, "resources": ["<li><span class=\"online_indicator\">ONLINE</span><i>Traveller Scottish: a language of United Kingdom.</i> n.a. 2013. SIL International.\n <a href=\"/item/oai:ethnologue.com:trl\">oai:ethnologue.com:trl</a></li>", "<li><span class=\"online_indicator\">ONLINE</span><i>LINGUIST List Resources for Scottish, Traveller.</i> Damir Cavar, Director of Linguist List (editor); Malgorzata E. Cavar, Director of Linguist List (editor). 2015-11-06. The LINGUIST List (www.linguistlist.org).\n <a href=\"/item/oai:linguistlist.org:lang_trl\">oai:linguistlist.org:lang_trl</a></li>"]}, "Language descriptions": {"count": 1, "resources": ["<li><span class=\"online_indicator\">ONLINE</span><i>Glottolog 2.6 Resources for Traveller Scottish.</i> n.a. 2014. Max Planck Institute for the Science of Human History.\n <a href=\"/item/oai:glottolog.org:trav1235\">oai:glottolog.org:trav1235</a></li>"]}}}