{"url": "http://www.language-archives.org/language/xkc", "code": "xkc", "coords": ["", "", "", ""], "name": "Kho'ini language", "resources": {"Other resources about the language": {"count": 1, "resources": ["<li><span class=\"online_indicator\">ONLINE</span><i>Kho'ini: a language of Iran.</i> n.a. 2013. SIL International.\n <a href=\"/item/oai:ethnologue.com:xkc\">oai:ethnologue.com:xkc</a></li>"]}, "Language descriptions": {"count": 1, "resources": ["<li><span class=\"online_indicator\">ONLINE</span><i>Glottolog 2.6 Resources for Kho'ini.</i> n.a. 2015. Max Planck Institute for the Science of Human History.\n <a href=\"/item/oai:glottolog.org:khoi1250\">oai:glottolog.org:khoi1250</a></li>"]}}}